CHANGES.rst
LICENSE.txt
MANIFEST.in
README.rst
setup.cfg
setup.py
asynclxd/__init__.py
asynclxd/lxc.py
asynclxd/remote.py
asynclxd/uri.py
asynclxd.egg-info/PKG-INFO
asynclxd.egg-info/SOURCES.txt
asynclxd.egg-info/dependency_links.txt
asynclxd.egg-info/entry_points.txt
asynclxd.egg-info/requires.txt
asynclxd.egg-info/top_level.txt
asynclxd/api/__init__.py
asynclxd/api/http.py
asynclxd/api/resource.py
asynclxd/api/testing.py
asynclxd/api/websocket.py
asynclxd/api/resources/__init__.py
asynclxd/api/resources/certificates.py
asynclxd/api/resources/containers.py
asynclxd/api/resources/events.py
asynclxd/api/resources/images.py
asynclxd/api/resources/networks.py
asynclxd/api/resources/operations.py
asynclxd/api/resources/profiles.py
asynclxd/api/resources/storage.py
asynclxd/api/resources/tests/__init__.py
asynclxd/api/resources/tests/test_containers.py
asynclxd/api/resources/tests/test_events.py
asynclxd/api/resources/tests/test_images.py
asynclxd/api/resources/tests/test_operations.py
asynclxd/api/resources/tests/test_storage.py
asynclxd/api/tests/__init__.py
asynclxd/api/tests/test_http.py
asynclxd/api/tests/test_resource.py
asynclxd/api/tests/test_websocket.py
asynclxd/tests/__init__.py
asynclxd/tests/test_lxc.py
asynclxd/tests/test_remote.py
asynclxd/tests/test_uri.py