Metadata-Version: 2.1
Name: asynclxd
Version: 0.0.1
Summary: Asynchronous client library for LXD REST API
Home-page: https://github.com/albertodonato/asynclxd
Author: Alberto Donato
Author-email: alberto.donato@gmail.com
Maintainer: Alberto Donato
Maintainer-email: alberto.donato@gmail.com
License: LGPLv3+
Keywords: asyncio LXD REST API
Platform: UNKNOWN
Classifier: Development Status :: 3 - Alpha
Classifier: License :: OSI Approved :: GNU Lesser General Public License v3 or later (LGPLv3+)
Classifier: Programming Language :: Python :: 3
Requires-Python: >= 3.6
Provides-Extra: testing
